gpm/__init__.py
gpm/__main__.py
git_project_manager-0.1.0rc0.dist-info/LICENSE
git_project_manager-0.1.0rc0.dist-info/METADATA
git_project_manager-0.1.0rc0.dist-info/WHEEL
git_project_manager-0.1.0rc0.dist-info/entry_points.txt
git_project_manager-0.1.0rc0.dist-info/top_level.txt
git_project_manager-0.1.0rc0.dist-info/RECORD
